tests/__init__.py
tests/test_allFileMetadata.py
tests/test_fileFilter.py
tests/test_fileMetadata.py
tests/test_flagController.py
tests/test_utils.py
twinTrim/__init__.py
twinTrim/flagController.py
twinTrim/flags.py
twinTrim/main.py
twinTrim/utils.py
twinTrim/dataStructures/__init__.py
twinTrim/dataStructures/allFileMetadata.py
twinTrim/dataStructures/fileFilter.py
twinTrim/dataStructures/fileMetadata.py
twinTrim-0.1.1.dist-info/LICENSE
twinTrim-0.1.1.dist-info/METADATA
twinTrim-0.1.1.dist-info/WHEEL
twinTrim-0.1.1.dist-info/entry_points.txt
twinTrim-0.1.1.dist-info/top_level.txt
twinTrim-0.1.1.dist-info/RECORD
