Metadata-Version: 2.1
Name: twinTrim
Version: 0.1.1
Summary: A CLI tool to find and delete duplicate files in a directory.
Home-page: https://github.com/kota-karthik/twinTrim
Author: Kota-Karthik
Author-email: kotakarthik2307@gmail.com
Classifier: Programming Language :: Python :: 3
Classifier: License :: OSI Approved :: MIT License
Classifier: Operating System :: OS Independent
Requires-Python: >=3.8
License-File: LICENSE
Requires-Dist: click>=8.0
Requires-Dist: tqdm>=4.66.5
Requires-Dist: mkdocs>=1.6.1
Requires-Dist: mkdocs-material>=9.5.44
Provides-Extra: dev
Requires-Dist: pytest>=8.3.3; extra == "dev"
Requires-Dist: pytest-mock>=3.14.0; extra == "dev"
